app_metrics/__init__.py
app_metrics/admin.py
app_metrics/exceptions.py
app_metrics/managers.py
app_metrics/models.py
app_metrics/reports.py
app_metrics/tasks.py
app_metrics/trending.py
app_metrics/urls.py
app_metrics/utils.py
app_metrics/views.py
app_metrics/backends/__init__.py
app_metrics/backends/composite.py
app_metrics/backends/db.py
app_metrics/backends/librato.py
app_metrics/backends/mixpanel.py
app_metrics/backends/redis.py
app_metrics/backends/statsd.py
app_metrics/management/__init__.py
app_metrics/management/commands/__init__.py
app_metrics/management/commands/metrics_aggregate.py
app_metrics/management/commands/metrics_send_mail.py
app_metrics/management/commands/move_to_mixpanel.py
app_metrics/management/commands/move_to_statsd.py
app_metrics/migrations/0001_initial.py
app_metrics/migrations/0002_auto_20181008_1758.py
app_metrics/migrations/__init__.py
app_metrics/templates/app_metrics/email.html
app_metrics/templates/app_metrics/email.txt
app_metrics/templates/app_metrics/metric_report.html
app_metrics/templates/app_metrics/metric_report_breadcrumbs.html
app_metrics/templates/app_metrics/metric_report_content.html
app_metrics/templates/app_metrics/metric_reports.html
app_metrics/tests/__init__.py
app_metrics/tests/base_tests.py
app_metrics/tests/librato_tests.py
app_metrics/tests/mixpanel_tests.py
app_metrics/tests/redis_tests.py
app_metrics/tests/settings.py
app_metrics/tests/statsd_tests.py
app_metrics/tests/urls.py
pivotal_app_metrics-1.1.2.dist-info/LICENSE.txt
pivotal_app_metrics-1.1.2.dist-info/METADATA
pivotal_app_metrics-1.1.2.dist-info/RECORD
pivotal_app_metrics-1.1.2.dist-info/WHEEL
pivotal_app_metrics-1.1.2.dist-info/top_level.txt
