Metadata-Version: 2.1
Name: pivotal-app-metrics
Version: 1.1.2
Summary: django-app-metrics is a reusable Django application for tracking and emailing application metrics.
Home-page: https://github.com/pivotal-energy-solutions/django-app-metrics
Author: Pivotal Energy Solutions
Author-email: sklass@pivotalenergysolutions.com
License: UNKNOWN
Download-URL: https://github.com/pivotal-energy-solutions/django-app-metrics/archive/1.1.2.tar.gz
Keywords: django analytics development
Platform: UNKNOWN
Classifier: Development Status :: 4 - Beta
Classifier: Environment :: Web Environment
Classifier: Intended Audience :: Developers
Classifier: License :: OSI Approved :: BSD License
Classifier: Operating System :: OS Independent
Classifier: Programming Language :: Python :: 2
Classifier: Programming Language :: Python :: 2.7
Classifier: Framework :: Django
Requires-Dist: celery
Requires-Dist: django (<2,>=1.11)
